stakepy/__init__.py
stakepy/main.py
stakepy-1.0.2.dist-info/METADATA
stakepy-1.0.2.dist-info/WHEEL
stakepy-1.0.2.dist-info/top_level.txt
stakepy-1.0.2.dist-info/RECORD
